temporython/__init__.py
temporython/temporython_import.py
temporython/temporython_inline_process_files_library.py
temporython/temporython_inline_process_pipe_library.py
temporython/temporython_pipe_import.py
temporython/templates/process_file_lines.py.template
temporython/templates/process_file_lines_pipe_only.py.template
temporython/templates/process_files.py.template
temporython-0.8.1.data/scripts/temporython
temporython-0.8.1.dist-info/LICENSE
temporython-0.8.1.dist-info/METADATA
temporython-0.8.1.dist-info/WHEEL
temporython-0.8.1.dist-info/top_level.txt
temporython-0.8.1.dist-info/RECORD
