Metadata-Version: 2.1
Name: temporython
Version: 0.8.1
Summary: Generate temporary Python scripts to quickly process lines of text or whole text files.
Home-page: https://github.com/waterimp/temporython
Author: Lee Bush
License: MIT
Keywords: python code generator data processing
Platform: UNKNOWN
Classifier: Development Status :: 5 - Production/Stable
Classifier: Environment :: Console
Classifier: License :: OSI Approved :: MIT License
Classifier: Natural Language :: English
Classifier: Programming Language :: Python :: 3.5
Classifier: Programming Language :: Python :: 3 :: Only
Classifier: Programming Language :: Python :: Implementation :: CPython
Classifier: Topic :: Software Development :: Code Generators
Classifier: Topic :: Text Processing
Classifier: Topic :: Software Development :: Libraries :: Python Modules
Requires-Python: >=3.5
